emk/__init__.py
emk/hf_utils.py
emk/indexer.py
emk/py.typed
emk/schema.py
emk/sleep_cycle.py
emk/store.py
emk-0.2.0.dist-info/licenses/LICENSE
emk-0.2.0.dist-info/METADATA
emk-0.2.0.dist-info/WHEEL
emk-0.2.0.dist-info/top_level.txt
emk-0.2.0.dist-info/RECORD
