Metadata-Version: 2.4
Name: emk
Version: 0.2.0
Summary: Episodic Memory Kernel - An immutable, append-only ledger of agent experiences for AI systems
Author-email: Imran Siddique <imran-siddique@users.noreply.github.com>
License: MIT
Project-URL: Homepage, https://github.com/imran-siddique/emk
Project-URL: Repository, https://github.com/imran-siddique/emk
Project-URL: Documentation, https://github.com/imran-siddique/emk#readme
Project-URL: Issues, https://github.com/imran-siddique/emk/issues
Project-URL: Changelog, https://github.com/imran-siddique/emk/releases
Keywords: ai,agents,memory,episodic-memory,llm,autonomous-agents,vector-store,append-only,immutable
Classifier: Development Status :: 3 - Alpha
Classifier: Intended Audience :: Developers
Classifier: Intended Audience :: Science/Research
Classifier: License :: OSI Approved :: MIT License
Classifier: Operating System :: OS Independent
Classifier: Programming Language :: Python :: 3
Classifier: Programming Language :: Python :: 3.8
Classifier: Programming Language :: Python :: 3.9
Classifier: Programming Language :: Python :: 3.10
Classifier: Programming Language :: Python :: 3.11
Classifier: Programming Language :: Python :: 3.12
Classifier: Topic :: Scientific/Engineering :: Artificial Intelligence
Classifier: Topic :: Software Development :: Libraries :: Python Modules
Classifier: Typing :: Typed
Requires-Python: >=3.8
License-File: LICENSE
Requires-Dist: pydantic>=2.0.0
Requires-Dist: numpy>=1.20.0
Provides-Extra: chromadb
Requires-Dist: chromadb>=0.4.0; extra == "chromadb"
Provides-Extra: huggingface
Requires-Dist: huggingface_hub>=0.19.0; extra == "huggingface"
Provides-Extra: all
Requires-Dist: chromadb>=0.4.0; extra == "all"
Requires-Dist: huggingface_hub>=0.19.0; extra == "all"
Provides-Extra: dev
Requires-Dist: pytest>=7.0.0; extra == "dev"
Requires-Dist: pytest-cov>=4.0.0; extra == "dev"
Requires-Dist: black>=23.0.0; extra == "dev"
Requires-Dist: ruff>=0.1.0; extra == "dev"
Requires-Dist: mypy>=1.0.0; extra == "dev"
Requires-Dist: pre-commit>=3.0.0; extra == "dev"
Dynamic: license-file
